{
    "base_dir": "bmr",
    "log_level": "debug",
    "console_level": "trace",
    "log_writer": {
        "filename": "bmr/bmr.log"
    },
    "stat_collector": {
        "verbose": false
    },
    "log_forwarder": {
        "vendor": "slack",
        "address": "https://hooks.slack.com/services/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",
        "level": "info"
    },
    "relays": [
        {
            "name": "t2i",
            "src": {
                "address": "btp://NetXnHfVqm9iesp.tezos/KT1TB59icBYsd35ace93ZUrUEWvfZ7TgqY61",
                "endpoint": [
                    "http://localhost:8732"
                ],
                "options": {
                    "verifier": {
                        "blockHeight": 3368125
                    },  
                    "syncConcurrency": 100, 
                    "bmcManagement": "KT1HDwVVLSsfQXdgQAJZuCm2DoXemapHjtiM"
                },
                "offset": 3368125
            },
            "dst": {
                "address": "btp://0x1.icon/cxb6c3f7f2618e33000dff26295468b53616df4640",
                "endpoint": [
                    "https://ctz.solidwallet.io/api/v3"
                ],
                "options": {
                    "step_limit": 100000000
                },
                "key_store": {"version":3,"id":"208083ba-6500-48b3-8b72-4f3be5b7ef99","address":"hx3baf3eb77acc858db66c6b64c4394e5b8485c67c","crypto":{"ciphertext":"0c65ab452930e8c30fbd464af844312f59c84c51db7c9558a2109d1e2ff2fc71","cipherparams":{"iv":"bed35c38c82f33e904928760b102a278"},"cipher":"aes-128-ctr","kdf":"scrypt","kdfparams":{"dklen":32,"salt":"7ac0551ba163f280c72c1297eb02e209de47945c61d1d6feec94f57c0a6f0cce","n":16384,"r":8,"p":1},"mac":"c1d7126a19af46c2f2e2977be0809a438916b608e6a6b4b45044dbd45381e2e1"},"coinType":"icx"},
                  "key_password": "icon@123"
            }
        },
        {
            "name": "i2t",
            "src": {
                "address": "btp://0x1.icon/cxb6c3f7f2618e33000dff26295468b53616df4640",
                "endpoint": [
                    "https://ctz.solidwallet.io/api/v3"
                ],
                "options": {
                    "verifier": {
                        "blockHeight": 25700560,
                        "validatorsHash": "0xe15fd3392fae29a7f72168f408ab4085c5aa617e55fa42572f8ba24c0f771d85"
                    },
                    "syncConcurrency": 100
                },
                "offset": 25700560 
            },
            "dst": {
                "address": "btp://NetXnHfVqm9iesp.tezos/KT1TB59icBYsd35ace93ZUrUEWvfZ7TgqY61",
                "endpoint": [
                    "http://localhost:8732"
                ],
                "options": {
                    "gas_limit": 1040000,
                    "boost_gas_price": 1.5,
                    "tx_data_size_limit": 65536,
                    "bmcManagement": "KT1HDwVVLSsfQXdgQAJZuCm2DoXemapHjtiM"
                },
                "key_store": {
                    "address": "tz1ZPVxKiybvbV1GvELRJJpyE1xj1UpNpXMv",
                    "crypto": {
                        "cipher": "edskRz1HoD3cWkmWhCNS5LjBrJNWChGuKWB4HnVoN5UqVsUCpcNJR67ZxKs965u8RgRwptrtGc2ufYZoeECgB77RKm1gTbQ6eB"
                    },
                    "coinType": "xtz"
                },
                "key_password": "xyz"
            }
        }
    ]
}